thingi10k/__init__.py
thingi10k/_builder.py
thingi10k/_clip.py
thingi10k/_logging.py
thingi10k/_utils.py
thingi10k/py.typed
thingi10k-1.3.0.dist-info/licenses/LICENSE
thingi10k-1.3.0.dist-info/WHEEL
thingi10k-1.3.0.dist-info/METADATA
thingi10k-1.3.0.dist-info/RECORD
