Metadata-Version: 2.4
Name: thingi10k
Version: 1.3.0
Summary: Thingi10k: A dataset of 10,000 3D-printable models
Author-email: Qingnan Zhou <qz263@nyu.edu>, Alec Jacobson <jacobson@cs.toronto.edu>
Requires-Python: >=3.10
Classifier: License :: OSI Approved :: Apache Software License
License-File: LICENSE
Requires-Dist: datasets>=4.0
Requires-Dist: numpy>=1.22
Requires-Dist: polars>=1.0
Requires-Dist: lagrange-open>=6.29.0
Requires-Dist: open_clip_torch==3.0.0 ; extra == "clip"
Provides-Extra: clip
